bonk_mcp/__init__.py
bonk_mcp/server.py
bonk_mcp/settings.py
bonk_mcp/utils.py
bonk_mcp/core/jupiter.py
bonk_mcp/core/letsbonk.py
bonk_mcp/tests/test_ipfs.py
bonk_mcp/tools/__init__.py
bonk_mcp/tools/birdeye.py
bonk_mcp/tools/jupiter.py
bonk_mcp/tools/token_buyer.py
bonk_mcp/tools/token_launcher.py
bonk_mcp/tools/transfer.py
bonk_mcp-0.1.11.dist-info/METADATA
bonk_mcp-0.1.11.dist-info/WHEEL
bonk_mcp-0.1.11.dist-info/entry_points.txt
bonk_mcp-0.1.11.dist-info/RECORD
